README.md
setup.py
NotAOrm.egg-info/PKG-INFO
NotAOrm.egg-info/SOURCES.txt
NotAOrm.egg-info/dependency_links.txt
NotAOrm.egg-info/top_level.txt
notaorm/__init__.py
notaorm/condition.py
notaorm/datatype.py
notaorm/operator_enum.py
notaorm/query.py
notaorm/table.py
notaorm/sql/creation.py
notaorm/sql/option.py
notaorm/sql/order.py