Metadata-Version: 2.1
Name: NotAOrm
Version: 1.2.1
Summary: A sample python library for managing a SQLite database
Home-page: https://github.com/ludel/NotAOrm
Author: ludel
Author-email: ludel47@gmail.com
License: UNKNOWN
Platform: UNKNOWN
Classifier: Programming Language :: Python :: 3
Classifier: License :: OSI Approved :: MIT License
Classifier: Operating System :: OS Independent
Requires-Python: >=3.6
